mistral_ocr/__init__.py
mistral_ocr/__main__.py
mistral_ocr/cli.py
mistral_ocr/config.py
mistral_ocr/processor.py
mistral_ocr/utils.py
mistral_ocr_cli-1.0.2.dist-info/METADATA
mistral_ocr_cli-1.0.2.dist-info/WHEEL
mistral_ocr_cli-1.0.2.dist-info/entry_points.txt
mistral_ocr_cli-1.0.2.dist-info/licenses/LICENSE
mistral_ocr_cli-1.0.2.dist-info/RECORD
