Metadata-Version: 2.4
Name: mistral-ocr-cli
Version: 1.0.2
Summary: A clean command-line tool for OCR processing using Mistral AI's API
License: MIT
License-File: LICENSE
Keywords: ocr,mistral,pdf,cli,command-line,document-processing,text-extraction,image-processing
Author: Ruben Fernandez-Fuertes
Author-email: fernandezfuertesruben@gmail.com
Requires-Python: >=3.9,<4.0
Classifier: Development Status :: 5 - Production/Stable
Classifier: Environment :: Console
Classifier: Intended Audience :: Developers
Classifier: Intended Audience :: Science/Research
Classifier: License :: OSI Approved :: MIT License
Classifier: Operating System :: OS Independent
Classifier: Programming Language :: Python :: 3
Classifier: Programming Language :: Python :: 3.9
Classifier: Programming Language :: Python :: 3.10
Classifier: Programming Language :: Python :: 3.11
Classifier: Programming Language :: Python :: 3.12
Classifier: Programming Language :: Python :: 3.13
Classifier: Programming Language :: Python :: 3.14
Classifier: Topic :: Scientific/Engineering :: Artificial Intelligence
Classifier: Topic :: Software Development :: Libraries :: Python Modules
Classifier: Topic :: Text Processing
Classifier: Topic :: Utilities
Requires-Dist: Pillow (>=11.0.0,<12.0.0)
Requires-Dist: click (>=8.1.7,<9.0.0)
Requires-Dist: mistralai (>=1.0.0,<2.0.0)
Requires-Dist: pypdf (>=4.0.0,<5.0.0)
Requires-Dist: python-dotenv (>=1.0.0,<2.0.0)
Requires-Dist: rich (>=13.7.0,<14.0.0)
Project-URL: Homepage, https://github.com/rubenfernandez/mistral-ocr-cli
Project-URL: Repository, https://github.com/rubenfernandez/mistral-ocr-cli
